protein_turnover_website/__init__.py
protein_turnover_website/app.py
protein_turnover_website/cdn.toml
protein_turnover_website/commands.py
protein_turnover_website/config.py
protein_turnover_website/filemanager_ui.py
protein_turnover_website/flask_utils.py
protein_turnover_website/index_view.py
protein_turnover_website/inspect.py
protein_turnover_website/inspect_view.py
protein_turnover_website/jobs.py
protein_turnover_website/jobs_view.py
protein_turnover_website/jobsmanager.py
protein_turnover_website/logger.py
protein_turnover_website/non_user_config.py
protein_turnover_website/py.typed
protein_turnover_website/utils.py
protein_turnover_website/wsgi.py
protein_turnover_website/wsgi_view.py
protein_turnover_website/explorer/__init__.py
protein_turnover_website/explorer/explorer.py
protein_turnover_website/explorer/explorer_view.py
protein_turnover_website/explorer/templates/explorer-test.html
protein_turnover_website/explorer/templates/explorer.css
protein_turnover_website/explorer/templates/explorer.html
protein_turnover_website/explorer/templates/explorer.js
protein_turnover_website/explorer/templates/explorer.ts
protein_turnover_website/login/__init__.py
protein_turnover_website/login/database.py
protein_turnover_website/login/login_view.py
protein_turnover_website/login/templates/login.html
protein_turnover_website/login/templates/login.js
protein_turnover_website/login/templates/login.ts
protein_turnover_website/sqla/__init__.py
protein_turnover_website/sqla/export.py
protein_turnover_website/sqla/export.toml
protein_turnover_website/sqla/inspect.py
protein_turnover_website/sqla/peptides.toml
protein_turnover_website/sqla/proteins.toml
protein_turnover_website/static/favicon.ico
protein_turnover_website/static/img/PEB.Logo-Colour.CMYK-wt-notarc-opt.svgz
protein_turnover_website/static/img/UWA-Full-Hor-CMYK-wt-opt.svgz
protein_turnover_website/static/img/email-white.svgz
protein_turnover_website/static/img/enrichment.png
protein_turnover_website-0.8.0.dist-info/METADATA
protein_turnover_website-0.8.0.dist-info/WHEEL
protein_turnover_website-0.8.0.dist-info/entry_points.txt
protein_turnover_website-0.8.0.dist-info/licenses/LICENSE
protein_turnover_website-0.8.0.dist-info/RECORD
