Metadata-Version: 2.4
Name: protein-turnover-website
Version: 0.8.0
Summary: Protein Turnover web pipeline
Project-URL: Repository, https://github.com/arabidopsis/protein_turnover_website.git
Author-email: Ian Castleden <ian.castleden@uwa.edu.au>
License-Expression: MIT
License-File: LICENSE
Classifier: Development Status :: 4 - Beta
Classifier: Intended Audience :: Science/Research
Classifier: Programming Language :: Python :: 3 :: Only
Classifier: Topic :: Scientific/Engineering :: Bio-Informatics
Requires-Python: >=3.12
Requires-Dist: flask-login<0.7,>=0.6
Requires-Dist: flask<4,>=3.1
Requires-Dist: openpyxl<4,>=3.0
Requires-Dist: protein-turnover[psutil,unidecode]<0.9,>=0.8.0
Requires-Dist: python-dotenv<2,>=1.0.1
Requires-Dist: tomli-w<2,>=1.2.0
Requires-Dist: typing-extensions<5,>=4.8
Provides-Extra: cloudflare
Requires-Dist: cloudflare-challenge>=0.1.4; extra == 'cloudflare'
Provides-Extra: gunicorn
Requires-Dist: gunicorn<24,>=23.0.0; extra == 'gunicorn'
Provides-Extra: install
Requires-Dist: flask-nginx; extra == 'install'
Requires-Dist: gunicorn<24,>=23.0.0; extra == 'install'
